{
    "5a31e1ff_8a2d1e91_NBA": {
        "Home Team": "Boston",
        "Home Abv": "BOS",
        "Away Team": "Cleveland",
        "Away Abv": "CLE",
        "Home Spread": "-12.5",
        "Home Spread Odds": "-115",
        "Home ML": "-1000",
        "Away Spread": "+12.5",
        "Away Spread Odds": "-105",
        "Away ML": "+650",
        "Total Points": "212.5",
        "Over Odds": "-110",
        "Under Odds": "-110",
        "Time": "Today · 7:00 PM",
        "League": "NBA"
    },
    "48eb7bb_88f1c3e9_NBA": {
        "Home Team": "Okla City",
        "Home Abv": "OKC",
        "Away Team": "Dallas",
        "Away Abv": "DAL",
        "Home Spread": "-4.5",
        "Home Spread Odds": "-115",
        "Home ML": "-200",
        "Away Spread": "+4.5",
        "Away Spread Odds": "-105",
        "Away ML": "+165",
        "Total Points": "217.5",
        "Over Odds": "-115",
        "Under Odds": "-105",
        "Time": "Today · 9:30 PM",
        "League": "NBA"
    }
}