[
    {
        "MatchupID": "f5328492_48eb7bb_NBA",
        "Info Table": {
            "Away Team": "MIN Timberwolves",
            "Away Team Rank Name": "Minnesota",
            "Away Abv": "MIN",
            "Away ID": "f5328492",
            "Home Team": "DAL Mavericks",
            "Home Team Rank Name": "Dallas",
            "Home Abv": "DAL",
            "Home ID": "48eb7bb",
            "Start Time": "Today · 8:00 PM",
            "League": "NBA"
        },
        "Odds Table": {
            "Away Spread": "+1.5 (ESPN)",
            "Away Spread Odds": "-110 (ESPN)",
            "Away ML": "+100 (ESPN)",
            "Home Spread": "-1.5 (ESPN)",
            "Home Spread Odds": "-105 (Bovada)",
            "Home ML": "-115 (Bovada)",
            "Total": "207.5 (ESPN)",
            "Over Total Odds": "-110 (ESPN)",
            "Under Total Odds": "-105 (Bovada)"
        }
    },
    {
        "MatchupID": "d10f1db8_ccadb94e_MLB",
        "Info Table": {
            "Away Team": "CHI Cubs",
            "Away Team Rank Name": "Chi Cubs",
            "Away Abv": "CHC",
            "Away ID": "d10f1db8",
            "Home Team": "STL Cardinals",
            "Home Team Rank Name": "St. Louis",
            "Home Abv": "STL",
            "Home ID": "ccadb94e",
            "Start Time": "Live Game",
            "League": "MLB"
        },
        "Odds Table": {
            "Away Spread": "+1.5 (ESPN)",
            "Away Spread Odds": "−166 (DK)",
            "Away ML": "+124 (DK)",
            "Home Spread": "-1.5 (ESPN)",
            "Home Spread Odds": "+145 (ESPN)",
            "Home ML": "-140 (ESPN)",
            "Total": "8.5 (ESPN)",
            "Over Total Odds": "+100 (ESPN)",
            "Under Total Odds": "−102 (DK)"
        }
    }
]