[
    {
        "MatchupID": "8a2d1e91_5a31e1ff_NBA",
        "Info Table": {
            "Away Team": "BOS Celtics",
            "Away Team Rank Name": "Boston",
            "Away Abv": "BOS",
            "Away ID": "8a2d1e91",
            "Home Team": "CLE Cavaliers",
            "Home Team Rank Name": "Cleveland",
            "Home Abv": "CLE",
            "Home ID": "5a31e1ff",
            "Start Time": "Today · 7:00 PM",
            "League": "NBA"
        },
        "Odds Table": {
            "Away Spread": "-8.5 (ESPN)",
            "Away Spread Odds": "-110 (ESPN)",
            "Away ML": "-340 (ESPN)",
            "Home Spread": "+8.5 (ESPN)",
            "Home Spread Odds": "-110 (ESPN)",
            "Home ML": "+280 (Bovada)",
            "Total": "206 (DK)",
            "Over Total Odds": "-110 (Bovada)",
            "Under Total Odds": "-105 (ESPN)"
        }
    },
    {
        "MatchupID": "88f1c3e9_48eb7bb_NBA",
        "Info Table": {
            "Away Team": "OKC Thunder",
            "Away Team Rank Name": "Okla City",
            "Away Abv": "OKC",
            "Away ID": "88f1c3e9",
            "Home Team": "DAL Mavericks",
            "Home Team Rank Name": "Dallas",
            "Home Abv": "DAL",
            "Home ID": "48eb7bb",
            "Start Time": "Today · 9:30 PM",
            "League": "NBA"
        },
        "Odds Table": {
            "Away Spread": "+1.5 (ESPN)",
            "Away Spread Odds": "-105 (Bovada)",
            "Away ML": "+100 (Bovada)",
            "Home Spread": "-1.0 (Bovada)",
            "Home Spread Odds": "+100 (ESPN)",
            "Home ML": "-115 (ESPN)",
            "Total": "213.5 (ESPN)",
            "Over Total Odds": "-105 (ESPN)",
            "Under Total Odds": "-110 (Bovada)"
        }
    }
]