[
    {
        "Away Team": "UIC",
        "DK Away Odds": {
            "Spread": "+7.5",
            "Spread Odds": "\u2212120",
            "Away ML": "+325"
        },
        "Home Team": "Missouri State",
        "DK Home Odds": {
            "Spread": "-7.5",
            "Spread Odds": "\u2212110",
            "Home ML": "\u2212475"
        },
        "Game": {
            "Start Time": "7:00PM",
            "Total": "144.5",
            "Over Total Odds": "\u2212120",
            "Under Total Odds": "\u2212110"
        }
    },
    {
        "Away Team": "UNI",
        "DK Away Odds": {
            "Spread": "+2.5",
            "Spread Odds": "\u2212120",
            "Away ML": "+124"
        },
        "Home Team": "Southern Illinois",
        "DK Home Odds": {
            "Spread": "-2.5",
            "Spread Odds": "\u2212110",
            "Home ML": "\u2212160"
        },
        "Game": {
            "Start Time": "9:00PM",
            "Total": "143.5",
            "Over Total Odds": "\u2212115",
            "Under Total Odds": "\u2212115"
        }
    },
    {
        "Away Team": "East Carolina",
        "DK Away Odds": {
            "Spread": "+9",
            "Spread Odds": "\u2212112",
            "Away ML": "+380"
        },
        "Home Team": "North Texas",
        "DK Home Odds": {
            "Spread": "-9",
            "Spread Odds": "\u2212108",
            "Home ML": "\u2212500"
        },
        "Game": {
            "Start Time": "3:05PM",
            "Total": "122.5",
            "Over Total Odds": "\u2212110",
            "Under Total Odds": "\u2212110"
        }
    },
    {
        "Away Team": "Kansas City",
        "DK Away Odds": {
            "Spread": "+2",
            "Spread Odds": "\u2212108",
            "Away ML": "+120"
        },
        "Home Team": "Oral Roberts",
        "DK Home Odds": {
            "Spread": "-2",
            "Spread Odds": "\u2212112",
            "Home ML": "\u2212142"
        },
        "Game": {
            "Start Time": "3:05PM",
            "Total": "142",
            "Over Total Odds": "\u2212112",
            "Under Total Odds": "\u2212108"
        }
    },
    {
        "Away Team": "Bradley",
        "DK Away Odds": {
            "Spread": "+4.5",
            "Spread Odds": "\u2212110",
            "Away ML": "+164"
        },
        "Home Team": "Drake",
        "DK Home Odds": {
            "Spread": "-4.5",
            "Spread Odds": "\u2212110",
            "Home ML": "\u2212198"
        },
        "Game": {
            "Start Time": "3:35PM",
            "Total": "149",
            "Over Total Odds": "+105",
            "Under Total Odds": "\u2212125"
        }
    },
    {
        "Away Team": "Michigan",
        "DK Away Odds": {
            "Spread": "+11.5",
            "Spread Odds": "\u2212108",
            "Away ML": "+525"
        },
        "Home Team": "Ohio State",
        "DK Home Odds": {
            "Spread": "-11.5",
            "Spread Odds": "\u2212112",
            "Home ML": "\u2212750"
        },
        "Game": {
            "Start Time": "4:05PM",
            "Total": "143.5",
            "Over Total Odds": "\u2212115",
            "Under Total Odds": "\u2212105"
        }
    },
    {
        "Away Team": "Murray State",
        "DK Away Odds": {
            "Spread": "+14",
            "Spread Odds": "\u2212110",
            "Away ML": "+750"
        },
        "Home Team": "Indiana State",
        "DK Home Odds": {
            "Spread": "-14",
            "Spread Odds": "\u2212112",
            "Home ML": "\u22121200"
        },
        "Game": {
            "Start Time": "4:05PM",
            "Total": "151",
            "Over Total Odds": "\u2212112",
            "Under Total Odds": "\u2212108"
        }
    },
    {
        "Away Team": "Evansville",
        "DK Away Odds": {
            "Spread": "+10.5",
            "Spread Odds": "\u2212110",
            "Away ML": "+470"
        },
        "Home Team": "Belmont",
        "DK Home Odds": {
            "Spread": "-10.5",
            "Spread Odds": "\u2212110",
            "Home ML": "\u2212650"
        },
        "Game": {
            "Start Time": "5:05PM",
            "Total": "154",
            "Over Total Odds": "\u2212118",
            "Under Total Odds": "\u2212102"
        }
    },
    {
        "Away Team": "UAB",
        "DK Away Odds": {
            "Spread": "+7.5",
            "Spread Odds": "\u2212110",
            "Away ML": "+270"
        },
        "Home Team": "Memphis",
        "DK Home Odds": {
            "Spread": "-7.5",
            "Spread Odds": "\u2212110",
            "Home ML": "\u2212340"
        },
        "Game": {
            "Start Time": "5:35PM",
            "Total": "158",
            "Over Total Odds": "\u2212118",
            "Under Total Odds": "\u2212102"
        }
    },
    {
        "Away Team": "Stanford",
        "DK Away Odds": {
            "Spread": "+12",
            "Spread Odds": "\u2212112",
            "Away ML": "+625"
        },
        "Home Team": "Colorado",
        "DK Home Odds": {
            "Spread": "-12",
            "Spread Odds": "\u2212108",
            "Home ML": "\u2212950"
        },
        "Game": {
            "Start Time": "9:05PM",
            "Total": "155.5",
            "Over Total Odds": "\u2212112",
            "Under Total Odds": "\u2212108"
        }
    }
]