[
    [
        {
            "BetTableId": "DK_4e2f3aa1_2b1ac347_MLB",
            "Odds Table": {
                "Book Name": "DK",
                "Away Spread": "-6.5",
                "Away Spread Odds": "+105",
                "Away ML": "−20000",
                "Home Spread": "+6.5",
                "Home Spread Odds": "−135",
                "Home ML": "+3000",
                "Total": "9.5",
                "Over Total Odds": "−120",
                "Under Total Odds": "−110"
            },
            "MatchupID": "4e2f3aa1_2b1ac347_MLB",
            "Info Table": {
                "Away Team": "LA Dodgers",
                "Away Team Rank Name": "LA Dodgers",
                "Away Abv": "LAD",
                "Away ID": "4e2f3aa1",
                "Home Team": "ARI Diamondbacks",
                "Home Team Rank Name": "Arizona",
                "Home Abv": "ARI",
                "Home ID": "2b1ac347",
                "Start Time": "Live Game",
                "League": "MLB"
            }
        }
    ]
]