{
    "c5227021_2848484e_NBA": {
        "Home Team": "Orlando",
        "Away Team": "Milwaukee",
        "Home Spread": "-6",
        "Home Spread Odds": "−112",
        "Away Spread": "+6",
        "Away Spread Odds": "−108",
        "Total Points": "215",
        "Over Odds": "−112",
        "Under Odds": "−108"
    },
    "6eb04a4e_fe2ec146_NBA": {
        "Home Team": "Philadelphia",
        "Away Team": "Brooklyn",
        "Home Spread": "-11.5",
        "Home Spread Odds": "−110",
        "Away Spread": "+11.5",
        "Away Spread Odds": "−110",
        "Total Points": "213",
        "Over Odds": "−112",
        "Under Odds": "−108"
    },
    "73c7ef49_5a31e1ff_NBA": {
        "Home Team": "Cleveland",
        "Away Team": "Charlotte",
        "Home Spread": "-14",
        "Home Spread Odds": "−112",
        "Away Spread": "+14",
        "Away Spread Odds": "−108",
        "Total Points": "208.5",
        "Over Odds": "−110",
        "Under Odds": "−110"
    },
    "f3d50c2_65ba1118_NBA": {
        "Home Team": "New York",
        "Away Team": "Chicago",
        "Home Spread": "-13",
        "Home Spread Odds": "−110",
        "Away Spread": "+13",
        "Away Spread Odds": "−110",
        "Total Points": "217.5",
        "Over Odds": "−108",
        "Under Odds": "−112"
    },
    "354ef58_dc435e0a_NBA": {
        "Home Team": "Indiana",
        "Away Team": "Atlanta",
        "Home Spread": "-14",
        "Home Spread Odds": "−112",
        "Away Spread": "+14",
        "Away Spread Odds": "−108",
        "Total Points": "241",
        "Over Odds": "−112",
        "Under Odds": "−108"
    },
    "dd4357ee_8a2d1e91_NBA": {
        "Home Team": "Boston",
        "Away Team": "Washington",
        "Home Spread": "-9.5",
        "Home Spread Odds": "−112",
        "Away Spread": "+9.5",
        "Away Spread Odds": "−108",
        "Total Points": "227.5",
        "Over Odds": "−112",
        "Under Odds": "−108"
    },
    "8714ddbe_8d47be6d_NBA": {
        "Home Team": "Miami",
        "Away Team": "Toronto",
        "Home Spread": "-16.5",
        "Home Spread Odds": "−108",
        "Away Spread": "+16.5",
        "Away Spread Odds": "−112",
        "Total Points": "218.5",
        "Over Odds": "−108",
        "Under Odds": "−112"
    },
    "5ed3c983_6a3773e4_NBA": {
        "Home Team": "New Orleans",
        "Away Team": "LA Lakers",
        "Home Spread": "-2.5",
        "Home Spread Odds": "−108",
        "Away Spread": "+2.5",
        "Away Spread Odds": "−112",
        "Total Points": "231.5",
        "Over Odds": "−108",
        "Under Odds": "−112"
    },
    "e52c9399_f5328492_NBA": {
        "Home Team": "Minnesota",
        "Away Team": "Phoenix",
        "Home Spread": "-1.5",
        "Home Spread Odds": "−112",
        "Away Spread": "+1.5",
        "Away Spread Odds": "−108",
        "Total Points": "217",
        "Over Odds": "−112",
        "Under Odds": "−108"
    },
    "b1e0538c_d608580b_NBA": {
        "Home Team": "Golden State",
        "Away Team": "Utah",
        "Home Spread": "-10",
        "Home Spread Odds": "−108",
        "Away Spread": "+10",
        "Away Spread Odds": "−112",
        "Total Points": "223",
        "Over Odds": "−110",
        "Under Odds": "−110"
    },
    "48eb7bb_88f1c3e9_NBA": {
        "Home Team": "Okla City",
        "Away Team": "Dallas",
        "Home Spread": "-19",
        "Home Spread Odds": "−110",
        "Away Spread": "+19",
        "Away Spread Odds": "−110",
        "Total Points": "224.5",
        "Over Odds": "−110",
        "Under Odds": "−110"
    },
    "8e06f0a2_a5c7e8a3_NBA": {
        "Home Team": "Sacramento",
        "Away Team": "Portland",
        "Home Spread": "-17",
        "Home Spread Odds": "−110",
        "Away Spread": "+17",
        "Away Spread Odds": "−110",
        "Total Points": "213.5",
        "Over Odds": "−110",
        "Under Odds": "−110"
    },
    "59dd0ac4_d1e32cbe_NBA": {
        "Home Team": "Memphis",
        "Away Team": "Denver",
        "Home Spread": "+13",
        "Home Spread Odds": "−112",
        "Away Spread": "-13",
        "Away Spread Odds": "−108",
        "Total Points": "217",
        "Over Odds": "−110",
        "Under Odds": "−110"
    },
    "18a9d733_4dc7a657_NBA": {
        "Home Team": "San Antonio",
        "Away Team": "Detroit",
        "Home Spread": "-5",
        "Home Spread Odds": "−110",
        "Away Spread": "+5",
        "Away Spread Odds": "−110",
        "Total Points": "217",
        "Over Odds": "−110",
        "Under Odds": "−110"
    },
    "4005c299_88571b9e_NBA": {
        "Home Team": "LA Clippers",
        "Away Team": "Houston",
        "Home Spread": "+2.5",
        "Home Spread Odds": "−110",
        "Away Spread": "-2.5",
        "Away Spread Odds": "−110",
        "Total Points": "222",
        "Over Odds": "−110",
        "Under Odds": "−110"
    }
}