[
    [
        {
            "BetTableId": "Bovada_6424b504_8a2d1e91_MLB",
            "Odds Table": {
                "Book Name": "Bovada",
                "Away Spread": "-5.5",
                "Away Spread Odds": "-375",
                "Away ML": "-7500",
                "Home Spread": "-5.5",
                "Home Spread Odds": "+260",
                "Home ML": "+1600",
                "Total": "10.5",
                "Over Total Odds": "+190",
                "Under Total Odds": "-260"
            },
            "MatchupID": "6424b504_8a2d1e91_MLB",
            "Info Table": {
                "Away Team": "New York Yankees",
                "Away Team Rank Name": "NY Yankees",
                "Away Abv": "NYY",
                "Away ID": "6424b504",
                "Home Team": "Boston Red Sox",
                "Home Team Rank Name": "Boston",
                "Home Abv": "BOS",
                "Home ID": "8a2d1e91",
                "Start Time": "Top 9",
                "League": "MLB"
            }
        }
    ]
]