{
    "8f2512bc_8b214a89_MLB": {
        "Home Team": "Oakland",
        "Home Abv": "OAK",
        "Away Team": "Colorado",
        "Away Abv": "COL",
        "Home Spread": "-1.5",
        "Home Spread Odds": "-175",
        "Home ML": "+155",
        "Away Spread": "-1.5",
        "Away Spread Odds": "+135",
        "Away ML": "-205",
        "Total Points": "6.5",
        "Over Odds": "-105",
        "Under Odds": "-125",
        "Time": "Top 6",
        "League": "MLB"
    },
    "2b1ac347_4e2f3aa1_MLB": {
        "Home Team": "LA Dodgers",
        "Home Abv": "LAD",
        "Away Team": "Arizona",
        "Away Abv": "ARI",
        "Home Spread": "+1.5",
        "Home Spread Odds": "-105",
        "Home ML": "-275",
        "Away Spread": "+1.5",
        "Away Spread Odds": "-125",
        "Away ML": "+200",
        "Total Points": "5.5",
        "Over Odds": "-105",
        "Under Odds": "-125",
        "Time": "Bot 3",
        "League": "MLB"
    }
}