{
    "486a5e3b_4e2f3aa1_MLB": {
        "Home Team": "LA Dodgers",
        "Home Abv": "LAD",
        "Away Team": "SF Giants",
        "Away Abv": "SF",
        "Home Spread": "+2.0",
        "Home Spread Odds": "+100",
        "Home ML": "-900",
        "Away Spread": "+2.0",
        "Away Spread Odds": "-130",
        "Away ML": "+500",
        "Total Points": "8.0",
        "Over Odds": "-110",
        "Under Odds": "-120",
        "Time": "Bot 6",
        "League": "MLB"
    },
    "Unknown_Unknown_MLB": {
        "Home Team": "Unknown",
        "Home Abv": "Unknown",
        "Away Team": "Unknown",
        "Away Abv": "Unknown",
        "Home Spread": "-999",
        "Home Spread Odds": "99",
        "Home ML": "-999",
        "Away Spread": "-999",
        "Away Spread Odds": "99",
        "Away ML": "-999",
        "Total Points": "-999",
        "Over Odds": "-110",
        "Under Odds": "99",
        "Time": "-999",
        "League": "MLB"
    },
    "354ef58_c625b23e_MLB": {
        "Home Team": "NY Mets",
        "Home Abv": "NYM",
        "Away Team": "Atlanta",
        "Away Abv": "ATL",
        "Home Spread": "-1.5",
        "Home Spread Odds": "+200",
        "Home ML": "-109",
        "Away Spread": "+1.5",
        "Away Spread Odds": "-240",
        "Away ML": "-111",
        "Total Points": "7.0",
        "Over Odds": "-120",
        "Under Odds": "+100",
        "Time": "7:10 PM",
        "League": "MLB"
    }
}